cannai/__init__.py
cannai/cannai_class.py
cannai/version.py
cannai/model_compare/__init__.py
cannai/model_compare/base.py
cannai/model_compare/cal_score.py
cannai/model_compare/multiclass.py
cannai-0.6.55.dist-info/LICENCE.txt
cannai-0.6.55.dist-info/METADATA
cannai-0.6.55.dist-info/WHEEL
cannai-0.6.55.dist-info/top_level.txt
cannai-0.6.55.dist-info/RECORD
