Metadata-Version: 2.1
Name: cannai
Version: 0.6.55
Summary: data visualization for machine learning
Home-page: UNKNOWN
Author: Ryo Kinoshita
Author-email: Rkinoshi55@gmail.com
License: MIT
Requires-Dist: cloudpickle (>=1.6.0)
Requires-Dist: matplotlib (>=3.3.3)
Requires-Dist: numpy (>=1.19.4)
Requires-Dist: pandas (>=1.1.4)
Requires-Dist: scikit-learn (>=0.24.0rc1)
Requires-Dist: scipy (>=1.5.4)
Requires-Dist: xgboost (>=1.3.1)
Requires-Dist: seaborn (>=0.11.1)
Requires-Dist: delayed (>=0.11.0b1)
Requires-Dist: torch (>=1.9)
Requires-Dist: tensorflow (>=2.6)
Requires-Dist: keras (>=2.6)
Requires-Dist: mlxtend (>=0.19.0)
